pygenix/__init__.py
pygenix/ani.py
pygenix/utils.py
pygenix-1.0.dist-info/METADATA
pygenix-1.0.dist-info/WHEEL
pygenix-1.0.dist-info/top_level.txt
pygenix-1.0.dist-info/RECORD
